wagtailmodelsearch/__init__.py
wagtailmodelsearch/abstract_models.py
wagtailmodelsearch/apps.py
wagtailmodelsearch/conf.py
wagtailmodelsearch/index.py
wagtailmodelsearch/models.py
wagtailmodelsearch/query.py
wagtailmodelsearch/queryset.py
wagtailmodelsearch/signal_handlers.py
wagtailmodelsearch/tasks.py
wagtailmodelsearch/utils.py
wagtailmodelsearch/backends/__init__.py
wagtailmodelsearch/backends/base.py
wagtailmodelsearch/backends/elasticsearch7.py
wagtailmodelsearch/backends/elasticsearch8.py
wagtailmodelsearch/backends/elasticsearch9.py
wagtailmodelsearch/backends/elasticsearchbase.py
wagtailmodelsearch/backends/opensearch2.py
wagtailmodelsearch/backends/opensearch3.py
wagtailmodelsearch/backends/database/__init__.py
wagtailmodelsearch/backends/database/fallback.py
wagtailmodelsearch/backends/database/mysql/__init__.py
wagtailmodelsearch/backends/database/mysql/mysql.py
wagtailmodelsearch/backends/database/mysql/query.py
wagtailmodelsearch/backends/database/postgres/__init__.py
wagtailmodelsearch/backends/database/postgres/postgres.py
wagtailmodelsearch/backends/database/postgres/query.py
wagtailmodelsearch/backends/database/postgres/weights.py
wagtailmodelsearch/backends/database/sqlite/__init__.py
wagtailmodelsearch/backends/database/sqlite/query.py
wagtailmodelsearch/backends/database/sqlite/sqlite.py
wagtailmodelsearch/backends/database/sqlite/utils.py
wagtailmodelsearch/management/__init__.py
wagtailmodelsearch/management/commands/__init__.py
wagtailmodelsearch/management/commands/rebuild_modelsearch_index.py
wagtailmodelsearch/migrations/0001_initial.py
wagtailmodelsearch/migrations/0002_customise_indexentry.py
wagtailmodelsearch/migrations/__init__.py
wagtailmodelsearch/test/settings.py
wagtailmodelsearch/test/urls.py
wagtailmodelsearch/test/testapp/__init__.py
wagtailmodelsearch/test/testapp/apps.py
wagtailmodelsearch/test/testapp/models.py
wagtailmodelsearch/test/testapp/migrations/0001_initial.py
wagtailmodelsearch-1.1b1.dist-info/licenses/LICENSE
wagtailmodelsearch-1.1b1.dist-info/METADATA
wagtailmodelsearch-1.1b1.dist-info/WHEEL
wagtailmodelsearch-1.1b1.dist-info/top_level.txt
wagtailmodelsearch-1.1b1.dist-info/RECORD
