Metadata-Version: 2.4
Name: wagtailmodelsearch
Version: 1.1b1
Summary: A library for indexing Django models with Elasicsearch, OpenSearch or database and searching them with the Django ORM.
Author-email: Karl Hobley <karl@kaed.uk>
License-Expression: BSD-3-Clause
Project-URL: Homepage, https://github.com/kaedroho/django-modelsearch
Project-URL: Documentation, https://django-modelsearch.readthedocs.io/en/latest
Project-URL: Source, https://github.com/kaedroho/django-modelsearch
Project-URL: Repository, https://github.com/kaedroho/django-modelsearch
Project-URL: Issues, https://github.com/kaedroho/django-modelsearch/issues
Project-URL: Changelog, https://github.com/kaedroho/django-modelsearch/releases
Classifier: Development Status :: 5 - Production/Stable
Classifier: Environment :: Web Environment
Classifier: Framework :: Django
Classifier: Intended Audience :: Developers
Classifier: Operating System :: OS Independent
Classifier: Programming Language :: Python
Classifier: Programming Language :: Python :: 3
Classifier: Programming Language :: Python :: 3 :: Only
Classifier: Programming Language :: Python :: 3.12
Classifier: Programming Language :: Python :: 3.13
Classifier: Topic :: Software Development :: Libraries :: Python Modules
Requires-Python: >=3.10
License-File: LICENSE
Requires-Dist: Django<6,>5.0
Requires-Dist: django-tasks<0.9,>=0.7
Provides-Extra: test
Requires-Dist: dj-database-url<3,>=2.3.0; extra == "test"
Requires-Dist: psycopg<4,>=3.2.6; extra == "test"
Requires-Dist: mysqlclient<3,>=2.2.0; extra == "test"
Requires-Dist: django-modelcluster<7,>=6.4; extra == "test"
Requires-Dist: django-tasks<1,>=0.6.1; extra == "test"
Requires-Dist: django-taggit<7,>=6.1.0; extra == "test"
Requires-Dist: coverage<8,>=7.10.6; extra == "test"
Provides-Extra: docs
Requires-Dist: sphinx<9,>=8.2.3; extra == "docs"
Requires-Dist: sphinx-rtd-theme<4.0,>=3.0.2; extra == "docs"
Requires-Dist: myst-parser<5,>=4.0.1; extra == "docs"
Provides-Extra: dev
Requires-Dist: ruff==0.13.0; extra == "dev"
Requires-Dist: pre-commit==3.4.0; extra == "dev"
Dynamic: license-file
